OSMint/__init__.py
OSMint/functions.py
OSMint/main.py
OSMint/speed_and_grad_imputation.py
OSMint/sumo.py
OSMint-0.0.4.dist-info/LICENSE
OSMint-0.0.4.dist-info/METADATA
OSMint-0.0.4.dist-info/WHEEL
OSMint-0.0.4.dist-info/top_level.txt
OSMint-0.0.4.dist-info/RECORD
