Metadata-Version: 2.1
Name: OSMint
Version: 0.0.4
Summary: A python package for extracting signalized intersections from OpenStreetMap
Home-page: https://github.com/quao627/OSMint
Author: Ao Qu & Anirudh Valiveru
Author-email: qua@mit.edu
License: MIT
Platform: UNKNOWN
Classifier: Programming Language :: Python :: 3
Classifier: License :: OSI Approved :: MIT License
Classifier: Operating System :: OS Independent
License-File: LICENSE
